<molecule id="m1" title="#5" xmlns="http://www.xml-cml.org/schema" xmlns:sre="http://www.chemaccess.org/sre-schema">
    <atomArray>
        <atom id="a1" elementType="C" x2="12.8433" y2="-23.5074" formalCharge="0" hydrogenCount="3"/>
        <atom id="a2" elementType="C" x2="14.1733" y2="-23.5074" formalCharge="0" hydrogenCount="2"/>
        <atom id="a3" elementType="C" x2="16.3045" y2="-23.5074" formalCharge="0" hydrogenCount="2"/>
        <atom id="a4" elementType="C" x2="18.4357" y2="-23.5074" formalCharge="0" hydrogenCount="0"/>
        <atom id="a5" elementType="O" x2="19.3762" y2="-24.4478" formalCharge="0" hydrogenCount="1"/>
        <atom id="a6" elementType="H" x2="20.6609" y2="-24.4241" formalCharge="0" hydrogenCount="0"/>
        <atom id="a7" elementType="O" x2="18.4357" y2="-22.1774" formalCharge="0" hydrogenCount="0"/>
    </atomArray>
    <bondArray>
        <bond id="b1" atomRefs2="a1 a2" order="S"/>
        <bond id="b2" atomRefs2="a2 a3" order="S"/>
        <bond id="b3" atomRefs2="a3 a4" order="S"/>
        <bond id="b4" atomRefs2="a4 a7" order="D"/>
        <bond id="b5" atomRefs2="a4 a5" order="S"/>
        <bond id="b6" atomRefs2="a5 a6" order="S"/>
    </bondArray>
    <atomSet title="Aliphatic chain" id="as1" size="4" sre:condensed="C C H2 C H2 C H3" sre:formula="C4H7">a1 a2 a3 a4</atomSet>
    <atomSet title="Functional group" id="as2" size="3" sre:condensed="C O H O" sre:formula="CHO2" sre:name="Carboxylic acid">a4 a7 a5</atomSet>
    <atomSet title="Molecule" id="as3" size="6" sre:formula="C4H8O2">a1 a2 a3 a4 a5 a7</atomSet>
    <sre:annotations>
        <sre:annotation sre:speech="SRE_MSG_0" sre:speech2="SRE_MSG_1">
            <sre:atom sre:type="Carbon">a1</sre:atom>
            <sre:parents>
                <sre:atomSet>as1</sre:atomSet>
            </sre:parents>
            <sre:position>4</sre:position>
            <sre:children/>
            <sre:component>
                <sre:bond>b1</sre:bond>
            </sre:component>
            <sre:neighbours>
                <sre:neighbour sre:speech="SRE_MSG_2" sre:speech2="SRE_MSG_3" sre:location="internal">
                    <sre:atom sre:type="Carbon">a2</sre:atom>
                    <sre:via sre:type="Connecting bond">
                        <sre:bond sre:type="single">b1</sre:bond>
                        <sre:position>3</sre:position>
                    </sre:via>
                </sre:neighbour>
            </sre:neighbours>
        </sre:annotation>
        <sre:annotation sre:speech="SRE_MSG_4" sre:speech2="SRE_MSG_5">
            <sre:atom sre:type="Carbon">a2</sre:atom>
            <sre:parents>
                <sre:atomSet>as1</sre:atomSet>
            </sre:parents>
            <sre:position>3</sre:position>
            <sre:children/>
            <sre:component>
                <sre:bond>b2</sre:bond>
                <sre:bond>b1</sre:bond>
            </sre:component>
            <sre:neighbours>
                <sre:neighbour sre:speech="SRE_MSG_6" sre:speech2="SRE_MSG_7" sre:location="internal">
                    <sre:atom sre:type="Carbon">a1</sre:atom>
                    <sre:via sre:type="Connecting bond">
                        <sre:bond sre:type="single">b1</sre:bond>
                        <sre:position>4</sre:position>
                    </sre:via>
                </sre:neighbour>
                <sre:neighbour sre:speech="SRE_MSG_8" sre:speech2="SRE_MSG_9" sre:location="internal">
                    <sre:atom sre:type="Carbon">a3</sre:atom>
                    <sre:via sre:type="Connecting bond">
                        <sre:bond sre:type="single">b2</sre:bond>
                        <sre:position>2</sre:position>
                    </sre:via>
                </sre:neighbour>
            </sre:neighbours>
        </sre:annotation>
        <sre:annotation sre:speech="SRE_MSG_10" sre:speech2="SRE_MSG_11">
            <sre:atom sre:type="Carbon">a3</sre:atom>
            <sre:parents>
                <sre:atomSet>as1</sre:atomSet>
            </sre:parents>
            <sre:position>2</sre:position>
            <sre:children/>
            <sre:component>
                <sre:bond>b2</sre:bond>
                <sre:bond>b3</sre:bond>
            </sre:component>
            <sre:neighbours>
                <sre:neighbour sre:speech="SRE_MSG_12" sre:speech2="SRE_MSG_13" sre:location="internal">
                    <sre:atom sre:type="Carbon">a2</sre:atom>
                    <sre:via sre:type="Connecting bond">
                        <sre:bond sre:type="single">b2</sre:bond>
                        <sre:position>3</sre:position>
                    </sre:via>
                </sre:neighbour>
                <sre:neighbour sre:speech="SRE_MSG_14" sre:speech2="SRE_MSG_15" sre:location="internal">
                    <sre:atom sre:type="Carbon">a4</sre:atom>
                    <sre:via sre:type="Connecting bond">
                        <sre:bond sre:type="single">b3</sre:bond>
                        <sre:position>1</sre:position>
                    </sre:via>
                </sre:neighbour>
            </sre:neighbours>
        </sre:annotation>
        <sre:annotation sre:speech="SRE_MSG_16" sre:speech2="SRE_MSG_17">
            <sre:atom sre:type="Carbon">a4</sre:atom>
            <sre:parents>
                <sre:atomSet>as1</sre:atomSet>
            </sre:parents>
            <sre:position>1</sre:position>
            <sre:children/>
            <sre:component>
                <sre:bond>b3</sre:bond>
            </sre:component>
            <sre:neighbours>
                <sre:neighbour sre:speech="SRE_MSG_18" sre:speech2="SRE_MSG_19" sre:location="internal">
                    <sre:atom sre:type="Carbon">a3</sre:atom>
                    <sre:via sre:type="Connecting bond">
                        <sre:bond sre:type="single">b3</sre:bond>
                        <sre:position>2</sre:position>
                    </sre:via>
                </sre:neighbour>
                <sre:neighbour sre:speech="SRE_MSG_20" sre:speech2="SRE_MSG_21" sre:location="external">
                    <sre:atom sre:type="Oxygen">a7</sre:atom>
                    <sre:via sre:type="Connecting bond">
                        <sre:bond sre:type="double">b4</sre:bond>
                        <sre:position>0</sre:position>
                    </sre:via>
                </sre:neighbour>
                <sre:neighbour sre:speech="SRE_MSG_22" sre:speech2="SRE_MSG_23" sre:location="external">
                    <sre:atom sre:type="Oxygen">a5</sre:atom>
                    <sre:via sre:type="Connecting bond">
                        <sre:bond sre:type="single">b5</sre:bond>
                        <sre:position>0</sre:position>
                    </sre:via>
                </sre:neighbour>
            </sre:neighbours>
        </sre:annotation>
        <sre:annotation sre:speech="SRE_MSG_24" sre:speech2="SRE_MSG_25">
            <sre:atom sre:type="Carbon">a4</sre:atom>
            <sre:parents>
                <sre:atomSet>as2</sre:atomSet>
            </sre:parents>
            <sre:position>1</sre:position>
            <sre:children/>
            <sre:component>
                <sre:bond>b4</sre:bond>
                <sre:bond>b5</sre:bond>
            </sre:component>
            <sre:neighbours>
                <sre:neighbour sre:speech="SRE_MSG_26" sre:speech2="SRE_MSG_27" sre:location="external">
                    <sre:atom sre:type="Carbon">a3</sre:atom>
                    <sre:via sre:type="Connecting bond">
                        <sre:bond sre:type="single">b3</sre:bond>
                        <sre:position>0</sre:position>
                    </sre:via>
                </sre:neighbour>
                <sre:neighbour sre:speech="SRE_MSG_28" sre:speech2="SRE_MSG_29" sre:location="internal">
                    <sre:atom sre:type="Oxygen">a7</sre:atom>
                    <sre:via sre:type="Connecting bond">
                        <sre:bond sre:type="double">b4</sre:bond>
                        <sre:position>3</sre:position>
                    </sre:via>
                </sre:neighbour>
                <sre:neighbour sre:speech="SRE_MSG_30" sre:speech2="SRE_MSG_31" sre:location="internal">
                    <sre:atom sre:type="Oxygen">a5</sre:atom>
                    <sre:via sre:type="Connecting bond">
                        <sre:bond sre:type="single">b5</sre:bond>
                        <sre:position>2</sre:position>
                    </sre:via>
                </sre:neighbour>
            </sre:neighbours>
        </sre:annotation>
        <sre:annotation sre:speech="SRE_MSG_32" sre:speech2="SRE_MSG_33">
            <sre:atom sre:type="Oxygen">a5</sre:atom>
            <sre:parents>
                <sre:atomSet>as2</sre:atomSet>
            </sre:parents>
            <sre:position>2</sre:position>
            <sre:children/>
            <sre:component>
                <sre:bond>b5</sre:bond>
                <sre:bond>b6</sre:bond>
            </sre:component>
            <sre:neighbours>
                <sre:neighbour sre:speech="SRE_MSG_34" sre:speech2="SRE_MSG_35" sre:location="internal">
                    <sre:atom sre:type="Carbon">a4</sre:atom>
                    <sre:via sre:type="Connecting bond">
                        <sre:bond sre:type="single">b5</sre:bond>
                        <sre:position>1</sre:position>
                    </sre:via>
                </sre:neighbour>
            </sre:neighbours>
        </sre:annotation>
        <sre:annotation sre:speech="SRE_MSG_36" sre:speech2="SRE_MSG_37">
            <sre:atom sre:type="Oxygen">a7</sre:atom>
            <sre:parents>
                <sre:atomSet>as2</sre:atomSet>
            </sre:parents>
            <sre:position>3</sre:position>
            <sre:children/>
            <sre:component>
                <sre:bond>b4</sre:bond>
            </sre:component>
            <sre:neighbours>
                <sre:neighbour sre:speech="SRE_MSG_38" sre:speech2="SRE_MSG_39" sre:location="internal">
                    <sre:atom sre:type="Carbon">a4</sre:atom>
                    <sre:via sre:type="Connecting bond">
                        <sre:bond sre:type="double">b4</sre:bond>
                        <sre:position>1</sre:position>
                    </sre:via>
                </sre:neighbour>
            </sre:neighbours>
        </sre:annotation>
        <sre:annotation sre:speech="SRE_MSG_40" sre:speech2="SRE_MSG_41">
            <sre:bond sre:type="single">b1</sre:bond>
            <sre:parents/>
            <sre:position>1</sre:position>
            <sre:children/>
            <sre:component>
                <sre:atom>a1</sre:atom>
                <sre:atom>a2</sre:atom>
            </sre:component>
            <sre:neighbours/>
        </sre:annotation>
        <sre:annotation sre:speech="SRE_MSG_42" sre:speech2="SRE_MSG_43">
            <sre:bond sre:type="single">b2</sre:bond>
            <sre:parents/>
            <sre:position>1</sre:position>
            <sre:children/>
            <sre:component>
                <sre:atom>a2</sre:atom>
                <sre:atom>a3</sre:atom>
            </sre:component>
            <sre:neighbours/>
        </sre:annotation>
        <sre:annotation sre:speech="SRE_MSG_44" sre:speech2="SRE_MSG_45">
            <sre:bond sre:type="single">b3</sre:bond>
            <sre:parents/>
            <sre:position>1</sre:position>
            <sre:children/>
            <sre:component>
                <sre:atom>a3</sre:atom>
                <sre:atom>a4</sre:atom>
            </sre:component>
            <sre:neighbours/>
        </sre:annotation>
        <sre:annotation sre:speech="SRE_MSG_46" sre:speech2="SRE_MSG_47">
            <sre:bond sre:type="double">b4</sre:bond>
            <sre:parents/>
            <sre:position>1</sre:position>
            <sre:children/>
            <sre:component>
                <sre:atom>a4</sre:atom>
                <sre:atom>a7</sre:atom>
            </sre:component>
            <sre:neighbours/>
        </sre:annotation>
        <sre:annotation sre:speech="SRE_MSG_48" sre:speech2="SRE_MSG_49">
            <sre:bond sre:type="single">b5</sre:bond>
            <sre:parents/>
            <sre:position>1</sre:position>
            <sre:children/>
            <sre:component>
                <sre:atom>a4</sre:atom>
                <sre:atom>a5</sre:atom>
            </sre:component>
            <sre:neighbours/>
        </sre:annotation>
        <sre:annotation sre:speech="SRE_MSG_50" sre:speech2="SRE_MSG_51">
            <sre:atomSet sre:type="Aliphatic chain">as1</sre:atomSet>
            <sre:parents>
                <sre:atomSet>as3</sre:atomSet>
            </sre:parents>
            <sre:position>1</sre:position>
            <sre:children>
                <sre:atom>a1</sre:atom>
                <sre:atom>a2</sre:atom>
                <sre:atom>a3</sre:atom>
                <sre:atom>a4</sre:atom>
            </sre:children>
            <sre:component>
                <sre:atom>a1</sre:atom>
                <sre:atom>a2</sre:atom>
                <sre:atom>a3</sre:atom>
                <sre:atom>a4</sre:atom>
                <sre:bond>b1</sre:bond>
                <sre:bond>b2</sre:bond>
                <sre:bond>b3</sre:bond>
            </sre:component>
            <sre:neighbours>
                <sre:neighbour sre:speech="SRE_MSG_52" sre:speech2="SRE_MSG_53">
                    <sre:atomSet sre:type="Functional group">as2</sre:atomSet>
                    <sre:via sre:type="Shared atom">
                        <sre:atom sre:type="Carbon">a4</sre:atom>
                        <sre:position>1</sre:position>
                    </sre:via>
                </sre:neighbour>
            </sre:neighbours>
        </sre:annotation>
        <sre:annotation sre:speech="SRE_MSG_54" sre:speech2="SRE_MSG_55">
            <sre:atomSet sre:type="Functional group">as2</sre:atomSet>
            <sre:parents>
                <sre:atomSet>as3</sre:atomSet>
            </sre:parents>
            <sre:position>2</sre:position>
            <sre:children>
                <sre:atom>a4</sre:atom>
                <sre:atom>a5</sre:atom>
                <sre:atom>a7</sre:atom>
            </sre:children>
            <sre:component>
                <sre:atom>a4</sre:atom>
                <sre:atom>a5</sre:atom>
                <sre:atom>a7</sre:atom>
                <sre:bond>b4</sre:bond>
                <sre:bond>b5</sre:bond>
                <sre:bond>b6</sre:bond>
                <sre:atom>a6</sre:atom>
            </sre:component>
            <sre:neighbours>
                <sre:neighbour sre:speech="SRE_MSG_56" sre:speech2="SRE_MSG_57">
                    <sre:atomSet sre:type="Aliphatic chain">as1</sre:atomSet>
                    <sre:via sre:type="Shared atom">
                        <sre:atom sre:type="Carbon">a4</sre:atom>
                        <sre:position>1</sre:position>
                    </sre:via>
                </sre:neighbour>
            </sre:neighbours>
        </sre:annotation>
        <sre:annotation sre:speech="SRE_MSG_58" sre:speech2="SRE_MSG_59">
            <sre:atomSet sre:type="Molecule">as3</sre:atomSet>
            <sre:parents/>
            <sre:position>1</sre:position>
            <sre:children>
                <sre:atomSet>as1</sre:atomSet>
                <sre:atomSet>as2</sre:atomSet>
            </sre:children>
            <sre:component>
                <sre:atom>a1</sre:atom>
                <sre:atom>a2</sre:atom>
                <sre:atom>a3</sre:atom>
                <sre:atom>a4</sre:atom>
                <sre:atom>a5</sre:atom>
                <sre:atom>a7</sre:atom>
                <sre:bond>b1</sre:bond>
                <sre:bond>b2</sre:bond>
                <sre:bond>b3</sre:bond>
                <sre:bond>b4</sre:bond>
                <sre:bond>b5</sre:bond>
                <sre:bond>b6</sre:bond>
                <sre:atom>a6</sre:atom>
            </sre:component>
            <sre:neighbours/>
        </sre:annotation>
        <sre:annotation>
            <sre:bond>b6</sre:bond>
            <sre:parents/>
            <sre:position>1</sre:position>
            <sre:component>
                <sre:atom>a6</sre:atom>
                <sre:atom>a5</sre:atom>
            </sre:component>
            <sre:neighbours/>
        </sre:annotation>
        <sre:annotation>
            <sre:atom sre:type="Hydrogen">a6</sre:atom>
            <sre:parents>
                <sre:atomSet>as2</sre:atomSet>
            </sre:parents>
            <sre:position>0</sre:position>
            <sre:component>
                <sre:bond>b6</sre:bond>
            </sre:component>
            <sre:neighbours/>
        </sre:annotation>
        <sre:messages>
            <sre:language>nl</sre:language>
            <sre:message sre:msg="SRE_MSG_0">Koolstof 4 met 3 gebonden waterstofatomen.</sre:message>
            <sre:message sre:msg="SRE_MSG_1">Koolstof 4 met 3 gebonden waterstofatomen.</sre:message>
            <sre:message sre:msg="SRE_MSG_10">Koolstof 2 met 2 gebonden waterstofatomen.</sre:message>
            <sre:message sre:msg="SRE_MSG_11">Koolstof 2 met 2 gebonden waterstofatomen.</sre:message>
            <sre:message sre:msg="SRE_MSG_12">Enkele binding met koolstof 3.</sre:message>
            <sre:message sre:msg="SRE_MSG_13">Enkele binding met koolstof 3.</sre:message>
            <sre:message sre:msg="SRE_MSG_14">Enkele binding met koolstof 1.</sre:message>
            <sre:message sre:msg="SRE_MSG_15">Enkele binding met koolstof 1.</sre:message>
            <sre:message sre:msg="SRE_MSG_16">Koolstof 1.</sre:message>
            <sre:message sre:msg="SRE_MSG_17">Koolstof 1.</sre:message>
            <sre:message sre:msg="SRE_MSG_18">Enkele binding met koolstof 2.</sre:message>
            <sre:message sre:msg="SRE_MSG_19">Enkele binding met koolstof 2.</sre:message>
            <sre:message sre:msg="SRE_MSG_2">Enkele binding met koolstof 3.</sre:message>
            <sre:message sre:msg="SRE_MSG_20">Dubbele binding met functionele groep carbonzuur.</sre:message>
            <sre:message sre:msg="SRE_MSG_21">Dubbele binding met functionele groep C O H O.</sre:message>
            <sre:message sre:msg="SRE_MSG_22">Enkele binding met functionele groep carbonzuur.</sre:message>
            <sre:message sre:msg="SRE_MSG_23">Enkele binding met functionele groep C O H O.</sre:message>
            <sre:message sre:msg="SRE_MSG_24">Koolstof 1.</sre:message>
            <sre:message sre:msg="SRE_MSG_25">Koolstof 1.</sre:message>
            <sre:message sre:msg="SRE_MSG_26">Enkele binding met butaan.</sre:message>
            <sre:message sre:msg="SRE_MSG_27">Enkele binding met koolstofketen met lengte 4.</sre:message>
            <sre:message sre:msg="SRE_MSG_28">Dubbele binding met zuurstof 3.</sre:message>
            <sre:message sre:msg="SRE_MSG_29">Dubbele binding met zuurstof 3.</sre:message>
            <sre:message sre:msg="SRE_MSG_3">Enkele binding met koolstof 3.</sre:message>
            <sre:message sre:msg="SRE_MSG_30">Enkele binding met zuurstof 2.</sre:message>
            <sre:message sre:msg="SRE_MSG_31">Enkele binding met zuurstof 2.</sre:message>
            <sre:message sre:msg="SRE_MSG_32">Zuurstof 2 met een gebonden waterstofatoom.</sre:message>
            <sre:message sre:msg="SRE_MSG_33">Zuurstof 2 met een gebonden waterstofatoom.</sre:message>
            <sre:message sre:msg="SRE_MSG_34">Enkele binding met koolstof 1.</sre:message>
            <sre:message sre:msg="SRE_MSG_35">Enkele binding met koolstof 1.</sre:message>
            <sre:message sre:msg="SRE_MSG_36">Zuurstof 3.</sre:message>
            <sre:message sre:msg="SRE_MSG_37">Zuurstof 3.</sre:message>
            <sre:message sre:msg="SRE_MSG_38">Dubbele binding met koolstof 1.</sre:message>
            <sre:message sre:msg="SRE_MSG_39">Dubbele binding met koolstof 1.</sre:message>
            <sre:message sre:msg="SRE_MSG_4">Koolstof 3 met 2 gebonden waterstofatomen.</sre:message>
            <sre:message sre:msg="SRE_MSG_40">Enkele binding.</sre:message>
            <sre:message sre:msg="SRE_MSG_41">Enkele binding.</sre:message>
            <sre:message sre:msg="SRE_MSG_42">Enkele binding.</sre:message>
            <sre:message sre:msg="SRE_MSG_43">Enkele binding.</sre:message>
            <sre:message sre:msg="SRE_MSG_44">Enkele binding.</sre:message>
            <sre:message sre:msg="SRE_MSG_45">Enkele binding.</sre:message>
            <sre:message sre:msg="SRE_MSG_46">Dubbele binding.</sre:message>
            <sre:message sre:msg="SRE_MSG_47">Dubbele binding.</sre:message>
            <sre:message sre:msg="SRE_MSG_48">Enkele binding.</sre:message>
            <sre:message sre:msg="SRE_MSG_49">Enkele binding.</sre:message>
            <sre:message sre:msg="SRE_MSG_5">Koolstof 3 met 2 gebonden waterstofatomen.</sre:message>
            <sre:message sre:msg="SRE_MSG_50">Butaan met substituent aan positie 1.</sre:message>
            <sre:message sre:msg="SRE_MSG_51">Koolstofketen met lengte 4 met substituent aan positie 1.</sre:message>
            <sre:message sre:msg="SRE_MSG_52">Gedeeld atoom koolstof 1 met functionele groep carbonzuur.</sre:message>
            <sre:message sre:msg="SRE_MSG_53">Gedeeld atoom koolstof 1 met functionele groep C O H O.</sre:message>
            <sre:message sre:msg="SRE_MSG_54">Functionele groep carbonzuur.</sre:message>
            <sre:message sre:msg="SRE_MSG_55">Functionele groep C O H O.</sre:message>
            <sre:message sre:msg="SRE_MSG_56">Gedeeld atoom koolstof 1 met butaan.</sre:message>
            <sre:message sre:msg="SRE_MSG_57">Gedeeld atoom koolstof 1 met koolstofketen met lengte 4.</sre:message>
            <sre:message sre:msg="SRE_MSG_58">Butaanzuur.</sre:message>
            <sre:message sre:msg="SRE_MSG_59">Molecuul bestaande uit een koolstofketen met lengte 4 en functionele groep C O H O.</sre:message>
            <sre:message sre:msg="SRE_MSG_6">Enkele binding met koolstof 4.</sre:message>
            <sre:message sre:msg="SRE_MSG_7">Enkele binding met koolstof 4.</sre:message>
            <sre:message sre:msg="SRE_MSG_8">Enkele binding met koolstof 2.</sre:message>
            <sre:message sre:msg="SRE_MSG_9">Enkele binding met koolstof 2.</sre:message>
        </sre:messages>
    </sre:annotations>
</molecule>